haicu/__haicu_ctl.py
haicu/__init__.py
haicu/__main__.py
haicu/format.py
haicu/ftdi.py
haicu-0.9.7.dist-info/LICENSE
haicu-0.9.7.dist-info/METADATA
haicu-0.9.7.dist-info/WHEEL
haicu-0.9.7.dist-info/entry_points.txt
haicu-0.9.7.dist-info/top_level.txt
haicu-0.9.7.dist-info/RECORD
