Metadata-Version: 2.1
Name: haicu
Version: 0.9.7
Summary: package for HAICU experiment
Author-email: Bryerton Shaw <bryerton@triumf.ca>
Maintainer-email: Bryerton Shaw <bryerton@triumf.ca>
License: MIT License
License-File: LICENSE
Requires-Dist: simplejson
Requires-Dist: pyftdi
Provides-Extra: dev
Requires-Dist: tox ; extra == 'dev'
